package com.app.aarti.lrc;

public class DefaultLrcBuilder
  implements ILrcBuilder
{
  static final String TAG = "DefaultLrcBuilder";
  
  /* Error */
  public java.util.List<LrcRow> getLrcRows(String paramString)
  {
    // Byte code:
    //   0: ldc 10
    //   2: ldc 22
    //   4: invokestatic 28	android/util/Log:d	(Ljava/lang/String;Ljava/lang/String;)I
    //   7: pop
    //   8: aload_1
    //   9: ifnull +10 -> 19
    //   12: aload_1
    //   13: invokevirtual 34	java/lang/String:length	()I
    //   16: ifne +13 -> 29
    //   19: ldc 10
    //   21: ldc 36
    //   23: invokestatic 39	android/util/Log:e	(Ljava/lang/String;Ljava/lang/String;)I
    //   26: pop
    //   27: aconst_null
    //   28: areturn
    //   29: new 41	java/io/StringReader
    //   32: dup
    //   33: aload_1
    //   34: invokespecial 44	java/io/StringReader:<init>	(Ljava/lang/String;)V
    //   37: astore 4
    //   39: new 46	java/io/BufferedReader
    //   42: dup
    //   43: aload 4
    //   45: invokespecial 49	java/io/BufferedReader:<init>	(Ljava/io/Reader;)V
    //   48: astore 5
    //   50: new 51	java/util/ArrayList
    //   53: dup
    //   54: invokespecial 52	java/util/ArrayList:<init>	()V
    //   57: astore 6
    //   59: aload 5
    //   61: invokevirtual 56	java/io/BufferedReader:readLine	()Ljava/lang/String;
    //   64: astore 12
    //   66: ldc 10
    //   68: new 58	java/lang/StringBuilder
    //   71: dup
    //   72: ldc 60
    //   74: invokespecial 61	java/lang/StringBuilder:<init>	(Ljava/lang/String;)V
    //   77: aload 12
    //   79: invokevirtual 65	java/lang/StringBuilder:append	(Ljava/lang/String;)Ljava/lang/StringBuilder;
    //   82: invokevirtual 68	java/lang/StringBuilder:toString	()Ljava/lang/String;
    //   85: invokestatic 28	android/util/Log:d	(Ljava/lang/String;Ljava/lang/String;)I
    //   88: pop
    //   89: aload 12
    //   91: ifnull +52 -> 143
    //   94: aload 12
    //   96: invokevirtual 34	java/lang/String:length	()I
    //   99: ifle +44 -> 143
    //   102: aload 12
    //   104: invokestatic 73	com/app/aarti/lrc/LrcRow:createRows	(Ljava/lang/String;)Ljava/util/List;
    //   107: astore 15
    //   109: aload 15
    //   111: ifnull +32 -> 143
    //   114: aload 15
    //   116: invokeinterface 78 1 0
    //   121: ifle +22 -> 143
    //   124: aload 15
    //   126: invokeinterface 82 1 0
    //   131: astore 16
    //   133: aload 16
    //   135: invokeinterface 88 1 0
    //   140: ifne +36 -> 176
    //   143: aload 12
    //   145: ifnonnull -86 -> 59
    //   148: aload 6
    //   150: invokeinterface 78 1 0
    //   155: ifle +8 -> 163
    //   158: aload 6
    //   160: invokestatic 94	java/util/Collections:sort	(Ljava/util/List;)V
    //   163: aload 5
    //   165: invokevirtual 97	java/io/BufferedReader:close	()V
    //   168: aload 4
    //   170: invokevirtual 98	java/io/StringReader:close	()V
    //   173: aload 6
    //   175: areturn
    //   176: aload 6
    //   178: aload 16
    //   180: invokeinterface 102 1 0
    //   185: checkcast 70	com/app/aarti/lrc/LrcRow
    //   188: invokeinterface 106 2 0
    //   193: pop
    //   194: goto -61 -> 133
    //   197: astore 9
    //   199: ldc 10
    //   201: new 58	java/lang/StringBuilder
    //   204: dup
    //   205: ldc 108
    //   207: invokespecial 61	java/lang/StringBuilder:<init>	(Ljava/lang/String;)V
    //   210: aload 9
    //   212: invokevirtual 111	java/lang/Exception:getMessage	()Ljava/lang/String;
    //   215: invokevirtual 65	java/lang/StringBuilder:append	(Ljava/lang/String;)Ljava/lang/StringBuilder;
    //   218: invokevirtual 68	java/lang/StringBuilder:toString	()Ljava/lang/String;
    //   221: invokestatic 39	android/util/Log:e	(Ljava/lang/String;Ljava/lang/String;)I
    //   224: pop
    //   225: aload 5
    //   227: invokevirtual 97	java/io/BufferedReader:close	()V
    //   230: aload 4
    //   232: invokevirtual 98	java/io/StringReader:close	()V
    //   235: aconst_null
    //   236: areturn
    //   237: astore 11
    //   239: aload 11
    //   241: invokevirtual 114	java/io/IOException:printStackTrace	()V
    //   244: goto -14 -> 230
    //   247: astore 7
    //   249: aload 5
    //   251: invokevirtual 97	java/io/BufferedReader:close	()V
    //   254: aload 4
    //   256: invokevirtual 98	java/io/StringReader:close	()V
    //   259: aload 7
    //   261: athrow
    //   262: astore 8
    //   264: aload 8
    //   266: invokevirtual 114	java/io/IOException:printStackTrace	()V
    //   269: goto -15 -> 254
    //   272: astore 14
    //   274: aload 14
    //   276: invokevirtual 114	java/io/IOException:printStackTrace	()V
    //   279: goto -111 -> 168
    // Local variable table:
    //   start	length	slot	name	signature
    //   0	282	0	this	DefaultLrcBuilder
    //   0	282	1	paramString	String
    //   37	218	4	localStringReader	java.io.StringReader
    //   48	202	5	localBufferedReader	java.io.BufferedReader
    //   57	120	6	localArrayList	java.util.ArrayList
    //   247	13	7	localObject	Object
    //   262	3	8	localIOException1	java.io.IOException
    //   197	14	9	localException	java.lang.Exception
    //   237	3	11	localIOException2	java.io.IOException
    //   64	80	12	str	String
    //   272	3	14	localIOException3	java.io.IOException
    //   107	18	15	localList	java.util.List
    //   131	48	16	localIterator	java.util.Iterator
    // Exception table:
    //   from	to	target	type
    //   59	89	197	java/lang/Exception
    //   94	109	197	java/lang/Exception
    //   114	133	197	java/lang/Exception
    //   133	143	197	java/lang/Exception
    //   148	163	197	java/lang/Exception
    //   176	194	197	java/lang/Exception
    //   225	230	237	java/io/IOException
    //   59	89	247	finally
    //   94	109	247	finally
    //   114	133	247	finally
    //   133	143	247	finally
    //   148	163	247	finally
    //   176	194	247	finally
    //   199	225	247	finally
    //   249	254	262	java/io/IOException
    //   163	168	272	java/io/IOException
  }
}


/* Location:           C:\Users\sahil.jain\Desktop\dex2jar-0.0.9.15\dex2jar-0.0.9.15\Aarti_com.app.aarti_1.0_1-dex2jar.jar
 * Qualified Name:     com.app.aarti.lrc.DefaultLrcBuilder
 * JD-Core Version:    0.7.0.1
 */